magicml/__init__.py
magicml-0.0.0.dist-info/METADATA
magicml-0.0.0.dist-info/WHEEL
magicml-0.0.0.dist-info/RECORD
