Metadata-Version: 2.1
Name: magicml
Version: 0.0.0
Summary: The machine learning model interface
License: BSD-3-Clause
Author: altar31
Author-email: damien.sicard31@gmail.com
Requires-Python: >=3.10
Classifier: License :: OSI Approved :: BSD License
Classifier: Programming Language :: Python :: 3
Classifier: Programming Language :: Python :: 3.10
Classifier: Programming Language :: Python :: 3.11
Requires-Dist: dash (>=2.11.1,<3.0.0)
Requires-Dist: keras (>=2.13.1,<3.0.0)
Requires-Dist: mlflow (>=2.5.0,<3.0.0)
Requires-Dist: pandas (>=2.0.3,<3.0.0)
Requires-Dist: scikit-learn (>=1.3.0,<2.0.0)
Requires-Dist: seaborn (>=0.12.2,<0.13.0)
